GifPlotter/__init__.py
GifPlotter/felixi_plotter.py
GifPlotter-0.1.2.dist-info/LICENSE
GifPlotter-0.1.2.dist-info/METADATA
GifPlotter-0.1.2.dist-info/WHEEL
GifPlotter-0.1.2.dist-info/top_level.txt
GifPlotter-0.1.2.dist-info/RECORD
