Metadata-Version: 2.1
Name: GifPlotter
Version: 0.1.2
Summary: A library to create and arrange plots and generate GIFs.
Home-page: https://github.com/yourusername/GifPlotter
Author: Amin Atashnezhad
Author-email: atashnezhad1@gmail.com
Classifier: Programming Language :: Python :: 3
Classifier: License :: OSI Approved :: MIT License
Classifier: Operating System :: OS Independent
Requires-Python: >=3.0
License-File: LICENSE
Requires-Dist: matplotlib
Requires-Dist: pandas
Requires-Dist: imageio
